MANIFEST.in
README.rst
changelog.txt
postinstalacion.py
setup.py
subtle/__init__.py
subtle/core.py
subtle/subtle.ico
subtle/utils.py
subtle.egg-info/PKG-INFO
subtle.egg-info/SOURCES.txt
subtle.egg-info/dependency_links.txt
subtle.egg-info/entry_points.txt
subtle.egg-info/requires.txt
subtle.egg-info/top_level.txt
subtle/bin/__init__.py
subtle/bin/main.py
subtle/webs/__init__.py
subtle/webs/addic7ed_com.py
subtle/webs/opensubtitles_org.py
subtle/webs/subtitulos_es.py