Metadata-Version: 1.1
Name: subtle
Version: 0.5
Summary: Descargador automático de subtítulos
Home-page: digitalwaste.wordpress.com
Author: Francisco Jesús Macía Espín(fmacia)
Author-email: fjmaciaespin@gmail.com
License: GPL v3
Download-URL: http://fmacia.github.com/subtle/
Platform: UNIX
Platform: Windows
Classifier: Development Status :: 3 - Alpha
Classifier: Environment :: Console
Classifier: Intended Audience :: End Users/Desktop
Classifier: License :: OSI Approved :: GNU General Public License v3 (GPLv3)
Classifier: Natural Language :: Spanish
Classifier: Operating System :: POSIX :: Linux
Classifier: Operating System :: Microsoft :: Windows
Classifier: Programming Language :: Python :: 2
Classifier: Programming Language :: Python :: 2.7
Classifier: Topic :: Multimedia :: Video
Classifier: Topic :: Software Development :: Libraries :: Python Modules
